qindomClient-1.0.7.dist-info/METADATA
qindomClient-1.0.7.dist-info/RECORD
qindomClient-1.0.7.dist-info/WHEEL
qindomClient-1.0.7.dist-info/top_level.txt
qit/Qclient.py
qit/__init__.py
qit/config.py
qit/utils/__init__.py
qit/utils/data_utils.py
qit/utils/preprocess.py
